eQTac/__init__.py
eQTac/control_FDR.py
eQTac/eQTac_correlation.py
eQTac/eQTac_permutation.py
eQTac/filter_bkg.py
eQTac/generate_PRE.py
eQTac/generate_mut_fa.py
eQTac/generate_snp_dict.py
eQTac/geno2score.py
eQTac/get_nullseq.py
eQTac-1.0.17.dist-info/LICENSE
eQTac-1.0.17.dist-info/METADATA
eQTac-1.0.17.dist-info/WHEEL
eQTac-1.0.17.dist-info/top_level.txt
eQTac-1.0.17.dist-info/RECORD
