Metadata-Version: 2.1
Name: eQTac
Version: 1.0.17
Summary: The eQTac method.
Home-page: https://github.com/JFF1594032292/eQTac
Author: Jiang Feng
Author-email: 1594032292@qq.com
License: UNKNOWN
Platform: UNKNOWN
Classifier: Programming Language :: Python :: 3
Classifier: License :: OSI Approved :: BSD License
Requires-Python: ==3.8
Requires-Dist: numpy (==1.22.4)
Requires-Dist: pandas (==1.4.3)
Requires-Dist: pybedtools (==0.8.2)
Requires-Dist: pysam (==0.16.0.1)
Requires-Dist: rpy2 (==3.5.11)
Requires-Dist: scipy (==1.8.1)
